<?xml version="1.0" encoding="UTF-8" standalone="no"?>
<!DOCTYPE svg PUBLIC "-//W3C//DTD SVG 1.1//EN"
 "http://www.w3.org/Graphics/SVG/1.1/DTD/svg11.dtd">
<!-- Generated by graphviz version 2.26.3 (20100126.1600)
 -->
<!-- Title: _anonymous_0 Pages: 1 -->
<svg width="5642pt" height="228pt"
 viewBox="0.00 0.00 5642.00 228.00" xmlns="http://www.w3.org/2000/svg" xmlns:xlink="http://www.w3.org/1999/xlink">
<g id="graph1" class="graph" transform="scale(1 1) rotate(0) translate(4 224)">
<title>_anonymous_0</title>
<polygon fill="white" stroke="white" points="-4,5 -4,-224 5639,-224 5639,5 -4,5"/>
<!-- Rhttp://dbpedia.org/page/Slayer -->
<g id="node1" class="node"><title>Rhttp://dbpedia.org/page/Slayer</title>
<a xlink:href="http://dbpedia.org/page/Slayer" xlink:title="http://dbpedia.org/page/Slayer">
<ellipse fill="none" stroke="blue" cx="1514" cy="-202" rx="155.849" ry="18"/>
<text text-anchor="middle" x="1514" y="-197.9" font-family="Times Roman,serif" font-size="14.00">http://dbpedia.org/page/Slayer</text>
</a>
</g>
<!-- Rhttp://purl.org/ontology/mo/MusicGroup -->
<g id="node3" class="node"><title>Rhttp://purl.org/ontology/mo/MusicGroup</title>
<a xlink:href="http://purl.org/ontology/mo/MusicGroup" xlink:title="http://purl.org/ontology/mo/MusicGroup">
<ellipse fill="none" stroke="blue" cx="201" cy="-111" rx="200.821" ry="18"/>
<text text-anchor="middle" x="201" y="-106.9" font-family="Times Roman,serif" font-size="14.00">http://purl.org/ontology/mo/MusicGroup</text>
</a>
</g>
<!-- Rhttp://dbpedia.org/page/Slayer&#45;&gt;Rhttp://purl.org/ontology/mo/MusicGroup -->
<g id="edge2" class="edge"><title>Rhttp://dbpedia.org/page/Slayer&#45;&gt;Rhttp://purl.org/ontology/mo/MusicGroup</title>
<path fill="none" stroke="black" d="M1359.64,-199.276C1073.06,-193.895 479.324,-181.103 386,-166 342.009,-158.881 293.795,-144.314 257.619,-131.96"/>
<polygon fill="black" stroke="black" points="258.343,-128.507 247.748,-128.542 256.053,-135.122 258.343,-128.507"/>
<text text-anchor="middle" x="413" y="-152.9" font-family="Times Roman,serif" font-size="14.00">rdf:type</text>
</g>
<!-- LSlayer -->
<g id="node5" class="node"><title>LSlayer</title>
<polygon fill="none" stroke="black" points="420,-93 420,-129 480,-129 480,-93 420,-93"/>
<text text-anchor="middle" x="450" y="-106.9" font-family="Times Roman,serif" font-size="14.00">Slayer</text>
</g>
<!-- Rhttp://dbpedia.org/page/Slayer&#45;&gt;LSlayer -->
<g id="edge4" class="edge"><title>Rhttp://dbpedia.org/page/Slayer&#45;&gt;LSlayer</title>
<path fill="none" stroke="black" d="M1359.35,-199.486C1068.29,-194.386 466.697,-181.945 451,-166 444.161,-159.053 442.617,-148.901 443.233,-139.205"/>
<polygon fill="black" stroke="black" points="446.736,-139.413 444.6,-129.036 439.798,-138.48 446.736,-139.413"/>
<text text-anchor="middle" x="485" y="-152.9" font-family="Times Roman,serif" font-size="14.00">foaf:name</text>
</g>
<!-- L1981 -->
<g id="node7" class="node"><title>L1981</title>
<polygon fill="none" stroke="black" points="324,-1 324,-37 378,-37 378,-1 324,-1"/>
<text text-anchor="middle" x="351" y="-14.9" font-family="Times Roman,serif" font-size="14.00">1981</text>
</g>
<!-- Rhttp://dbpedia.org/page/Slayer&#45;&gt;L1981 -->
<g id="edge6" class="edge"><title>Rhttp://dbpedia.org/page/Slayer&#45;&gt;L1981</title>
<path fill="none" stroke="black" d="M1360.21,-198.871C1213.22,-194.816 985.551,-185.757 789,-166 682.993,-155.344 652.201,-166.207 552,-130 521.247,-118.887 517.463,-108.096 489,-92 486.51,-90.5921 427.272,-59.2848 387.226,-38.1316"/>
<polygon fill="black" stroke="black" points="388.731,-34.968 378.254,-33.3922 385.461,-41.1576 388.731,-34.968"/>
</g>
<!-- LUnited States -->
<g id="node9" class="node"><title>LUnited States</title>
<polygon fill="none" stroke="black" points="560.5,-93 560.5,-129 671.5,-129 671.5,-93 560.5,-93"/>
<text text-anchor="middle" x="616" y="-106.9" font-family="Times Roman,serif" font-size="14.00">United States</text>
</g>
<!-- Rhttp://dbpedia.org/page/Slayer&#45;&gt;LUnited States -->
<g id="edge8" class="edge"><title>Rhttp://dbpedia.org/page/Slayer&#45;&gt;LUnited States</title>
<path fill="none" stroke="black" d="M1361.7,-198.091C1195.83,-191.726 923.004,-175.093 681.7,-130.139"/>
<polygon fill="black" stroke="black" points="682.159,-126.665 671.684,-128.254 680.864,-133.544 682.159,-126.665"/>
</g>
<!-- Rhttp://sws.geonames.org/5358736/ -->
<g id="node11" class="node"><title>Rhttp://sws.geonames.org/5358736/</title>
<a xlink:href="http://sws.geonames.org/5358736/" xlink:title="http://sws.geonames.org/5358736/">
<ellipse fill="none" stroke="blue" cx="869" cy="-111" rx="179.975" ry="18"/>
<text text-anchor="middle" x="869" y="-106.9" font-family="Times Roman,serif" font-size="14.00">http://sws.geonames.org/5358736/</text>
</a>
</g>
<!-- Rhttp://dbpedia.org/page/Slayer&#45;&gt;Rhttp://sws.geonames.org/5358736/ -->
<g id="edge10" class="edge"><title>Rhttp://dbpedia.org/page/Slayer&#45;&gt;Rhttp://sws.geonames.org/5358736/</title>
<path fill="none" stroke="black" d="M1414.98,-188.03C1298.63,-171.615 1105.92,-144.426 983.318,-127.129"/>
<polygon fill="black" stroke="black" points="983.538,-123.625 973.147,-125.694 982.56,-130.556 983.538,-123.625"/>
</g>
<!-- Rhttp://dbpedia.org/page/Thrash_metal -->
<g id="node13" class="node"><title>Rhttp://dbpedia.org/page/Thrash_metal</title>
<a xlink:href="http://dbpedia.org/page/Thrash_metal" xlink:title="http://dbpedia.org/page/Thrash_metal">
<ellipse fill="none" stroke="blue" cx="1259" cy="-111" rx="191.788" ry="18"/>
<text text-anchor="middle" x="1259" y="-106.9" font-family="Times Roman,serif" font-size="14.00">http://dbpedia.org/page/Thrash_metal</text>
</a>
</g>
<!-- Rhttp://dbpedia.org/page/Slayer&#45;&gt;Rhttp://dbpedia.org/page/Thrash_metal -->
<g id="edge12" class="edge"><title>Rhttp://dbpedia.org/page/Slayer&#45;&gt;Rhttp://dbpedia.org/page/Thrash_metal</title>
<path fill="none" stroke="black" d="M1465.74,-184.777C1423.63,-169.751 1362.43,-147.91 1317.54,-131.89"/>
<polygon fill="black" stroke="black" points="1318.53,-128.527 1307.93,-128.463 1316.18,-135.12 1318.53,-128.527"/>
</g>
<!-- B_:genid1 -->
<g id="node15" class="node"><title>B_:genid1</title>
<ellipse fill="none" stroke="green" cx="1487" cy="-111" rx="18" ry="18"/>
</g>
<!-- Rhttp://dbpedia.org/page/Slayer&#45;&gt;B_:genid1 -->
<g id="edge14" class="edge"><title>Rhttp://dbpedia.org/page/Slayer&#45;&gt;B_:genid1</title>
<path fill="none" stroke="black" d="M1508.54,-183.585C1504.69,-170.63 1499.48,-153.068 1495.15,-138.465"/>
<polygon fill="black" stroke="black" points="1498.38,-137.053 1492.18,-128.462 1491.67,-139.044 1498.38,-137.053"/>
</g>
<!-- B_:genid2 -->
<g id="node17" class="node"><title>B_:genid2</title>
<ellipse fill="none" stroke="green" cx="1541" cy="-111" rx="18" ry="18"/>
</g>
<!-- Rhttp://dbpedia.org/page/Slayer&#45;&gt;B_:genid2 -->
<g id="edge16" class="edge"><title>Rhttp://dbpedia.org/page/Slayer&#45;&gt;B_:genid2</title>
<path fill="none" stroke="black" d="M1519.46,-183.585C1523.31,-170.63 1528.52,-153.068 1532.85,-138.465"/>
<polygon fill="black" stroke="black" points="1536.33,-139.044 1535.82,-128.462 1529.62,-137.053 1536.33,-139.044"/>
</g>
<!-- B_:genid3 -->
<g id="node19" class="node"><title>B_:genid3</title>
<ellipse fill="none" stroke="green" cx="3085" cy="-111" rx="18" ry="18"/>
</g>
<!-- Rhttp://dbpedia.org/page/Slayer&#45;&gt;B_:genid3 -->
<g id="edge18" class="edge"><title>Rhttp://dbpedia.org/page/Slayer&#45;&gt;B_:genid3</title>
<path fill="none" stroke="black" d="M1646.38,-192.425C1806.55,-181.009 2084.45,-161.752 2323,-148 2609.44,-131.487 2956.75,-116.426 3056.8,-112.185"/>
<polygon fill="black" stroke="black" points="3057.15,-115.673 3066.99,-111.754 3056.85,-108.679 3057.15,-115.673"/>
</g>
<!-- B_:genid4 -->
<g id="node21" class="node"><title>B_:genid4</title>
<ellipse fill="none" stroke="green" cx="3601" cy="-111" rx="18" ry="18"/>
</g>
<!-- Rhttp://dbpedia.org/page/Slayer&#45;&gt;B_:genid4 -->
<g id="edge20" class="edge"><title>Rhttp://dbpedia.org/page/Slayer&#45;&gt;B_:genid4</title>
<path fill="none" stroke="black" d="M1660.34,-195.619C2095.88,-176.628 3366.36,-121.231 3572.57,-112.24"/>
<polygon fill="black" stroke="black" points="3573.02,-115.723 3582.86,-111.791 3572.72,-108.73 3573.02,-115.723"/>
</g>
<!-- B_:genid5 -->
<g id="node23" class="node"><title>B_:genid5</title>
<ellipse fill="none" stroke="green" cx="4122" cy="-111" rx="18" ry="18"/>
</g>
<!-- Rhttp://dbpedia.org/page/Slayer&#45;&gt;B_:genid5 -->
<g id="edge22" class="edge"><title>Rhttp://dbpedia.org/page/Slayer&#45;&gt;B_:genid5</title>
<path fill="none" stroke="black" d="M1664.28,-197.111C2010.57,-185.793 2891.51,-156.717 3628,-130 3804.99,-123.58 4017.62,-115.165 4093.44,-112.142"/>
<polygon fill="black" stroke="black" points="4093.76,-115.632 4103.61,-111.736 4093.48,-108.638 4093.76,-115.632"/>
</g>
<!-- B_:genid6 -->
<g id="node25" class="node"><title>B_:genid6</title>
<ellipse fill="none" stroke="green" cx="2112" cy="-111" rx="18" ry="18"/>
</g>
<!-- Rhttp://dbpedia.org/page/Slayer&#45;&gt;B_:genid6 -->
<g id="edge24" class="edge"><title>Rhttp://dbpedia.org/page/Slayer&#45;&gt;B_:genid6</title>
<path fill="none" stroke="black" d="M1608.42,-187.631C1747.47,-166.471 1999.93,-128.055 2083.95,-115.268"/>
<polygon fill="black" stroke="black" points="2084.65,-118.703 2094.01,-113.738 2083.6,-111.782 2084.65,-118.703"/>
</g>
<!-- B_:genid7 -->
<g id="node27" class="node"><title>B_:genid7</title>
<ellipse fill="none" stroke="green" cx="4994" cy="-111" rx="18" ry="18"/>
</g>
<!-- Rhttp://dbpedia.org/page/Slayer&#45;&gt;B_:genid7 -->
<g id="edge26" class="edge"><title>Rhttp://dbpedia.org/page/Slayer&#45;&gt;B_:genid7</title>
<path fill="none" stroke="black" d="M1666.33,-198.017C2296.22,-181.545 4677.82,-119.268 4965.5,-111.745"/>
<polygon fill="black" stroke="black" points="4965.99,-115.234 4975.9,-111.473 4965.81,-108.236 4965.99,-115.234"/>
</g>
<!-- LVersuch Nummer 1 -->
<g id="node29" class="node"><title>LVersuch Nummer 1</title>
<polygon fill="none" stroke="black" points="5029.5,-93 5029.5,-129 5178.5,-129 5178.5,-93 5029.5,-93"/>
<text text-anchor="middle" x="5104" y="-106.9" font-family="Times Roman,serif" font-size="14.00">Versuch Nummer 1</text>
</g>
<!-- Rhttp://dbpedia.org/page/Slayer&#45;&gt;LVersuch Nummer 1 -->
<g id="edge28" class="edge"><title>Rhttp://dbpedia.org/page/Slayer&#45;&gt;LVersuch Nummer 1</title>
<path fill="none" stroke="black" d="M1669.68,-200.68C2299.45,-195.087 4642.29,-171.743 5019.4,-129.995"/>
<polygon fill="black" stroke="black" points="5019.95,-133.455 5029.47,-128.817 5019.13,-126.502 5019.95,-133.455"/>
<text text-anchor="middle" x="4744.5" y="-152.9" font-family="Times Roman,serif" font-size="14.00">rdfs:label</text>
</g>
<!-- B_:genid1&#45;&gt;L1981 -->
<g id="edge38" class="edge"><title>B_:genid1&#45;&gt;L1981</title>
<path fill="none" stroke="black" d="M1473.29,-99.0349C1469.26,-96.1951 1464.68,-93.5442 1460,-92 1381.05,-65.9563 794.948,-79.5816 712,-74 707.867,-73.7219 444.504,-45.1104 388.163,-36.5149"/>
<polygon fill="black" stroke="black" points="388.532,-33.0235 378.06,-34.6309 387.249,-39.9048 388.532,-33.0235"/>
</g>
<!-- Rhttp://purl.org/ontology/mo/Membership -->
<g id="node31" class="node"><title>Rhttp://purl.org/ontology/mo/Membership</title>
<a xlink:href="http://purl.org/ontology/mo/Membership" xlink:title="http://purl.org/ontology/mo/Membership">
<ellipse fill="none" stroke="blue" cx="2722" cy="-19" rx="202.211" ry="18"/>
<text text-anchor="middle" x="2722" y="-14.9" font-family="Times Roman,serif" font-size="14.00">http://purl.org/ontology/mo/Membership</text>
</a>
</g>
<!-- B_:genid1&#45;&gt;Rhttp://purl.org/ontology/mo/Membership -->
<g id="edge30" class="edge"><title>B_:genid1&#45;&gt;Rhttp://purl.org/ontology/mo/Membership</title>
<path fill="none" stroke="black" d="M1500.72,-99.0446C1504.74,-96.2048 1509.32,-93.5515 1514,-92 1583.84,-68.8397 2108.02,-102.164 2176,-74 2186.75,-69.5477 2184.32,-60.6115 2195,-56 2259.57,-28.1158 2440.85,-43.1547 2511,-38 2531.17,-36.5175 2552.42,-34.795 2573.34,-33.004"/>
<polygon fill="black" stroke="black" points="2573.92,-36.4672 2583.58,-32.1201 2573.32,-29.4932 2573.92,-36.4672"/>
<text text-anchor="middle" x="2222" y="-60.9" font-family="Times Roman,serif" font-size="14.00">rdf:type</text>
</g>
<!-- Rhttp://njh.me/#Kerry_King -->
<g id="node33" class="node"><title>Rhttp://njh.me/#Kerry_King</title>
<a xlink:href="http://njh.me/#Kerry_King" xlink:title="http://njh.me/#Kerry_King">
<ellipse fill="none" stroke="blue" cx="533" cy="-19" rx="136.892" ry="18"/>
<text text-anchor="middle" x="533" y="-14.9" font-family="Times Roman,serif" font-size="14.00">http://njh.me/#Kerry_King</text>
</a>
</g>
<!-- B_:genid1&#45;&gt;Rhttp://njh.me/#Kerry_King -->
<g id="edge32" class="edge"><title>B_:genid1&#45;&gt;Rhttp://njh.me/#Kerry_King</title>
<path fill="none" stroke="black" d="M1473.28,-99.0489C1469.26,-96.2091 1464.68,-93.5547 1460,-92 1393.55,-69.9125 899.637,-81.3978 830,-74 755.073,-66.0402 670.691,-49.6888 611.072,-36.8736"/>
<polygon fill="black" stroke="black" points="611.494,-33.384 600.98,-34.6872 610.012,-40.2253 611.494,-33.384"/>
</g>
<!-- Lcurrent, guitar -->
<g id="node35" class="node"><title>Lcurrent, guitar</title>
<polygon fill="none" stroke="black" points="688,-1 688,-37 806,-37 806,-1 688,-1"/>
<text text-anchor="middle" x="747" y="-14.9" font-family="Times Roman,serif" font-size="14.00">current, guitar</text>
</g>
<!-- B_:genid1&#45;&gt;Lcurrent, guitar -->
<g id="edge34" class="edge"><title>B_:genid1&#45;&gt;Lcurrent, guitar</title>
<path fill="none" stroke="black" d="M1473.28,-99.0592C1469.26,-96.2195 1464.68,-93.5626 1460,-92 1341.07,-52.2502 1019.07,-98.0219 896,-74 860.987,-67.166 823.308,-53.1925 794.601,-41.041"/>
<polygon fill="black" stroke="black" points="795.795,-37.7444 785.226,-37.0028 793.026,-44.1734 795.795,-37.7444"/>
<text text-anchor="middle" x="927.5" y="-60.9" font-family="Times Roman,serif" font-size="14.00">rdfs:label</text>
</g>
<!-- Rhttp://dbpedia.org/page/Guitar -->
<g id="node37" class="node"><title>Rhttp://dbpedia.org/page/Guitar</title>
<a xlink:href="http://dbpedia.org/page/Guitar" xlink:title="http://dbpedia.org/page/Guitar">
<ellipse fill="none" stroke="blue" cx="1897" cy="-19" rx="157.043" ry="18"/>
<text text-anchor="middle" x="1897" y="-14.9" font-family="Times Roman,serif" font-size="14.00">http://dbpedia.org/page/Guitar</text>
</a>
</g>
<!-- B_:genid1&#45;&gt;Rhttp://dbpedia.org/page/Guitar -->
<g id="edge36" class="edge"><title>B_:genid1&#45;&gt;Rhttp://dbpedia.org/page/Guitar</title>
<path fill="none" stroke="black" d="M1500.9,-99.5362C1504.92,-96.6983 1509.46,-93.9231 1514,-92 1562.31,-71.5319 1692.54,-49.0855 1787.77,-34.5615"/>
<polygon fill="black" stroke="black" points="1788.39,-38.0089 1797.75,-33.0497 1787.34,-31.0879 1788.39,-38.0089"/>
</g>
<!-- B_:genid2&#45;&gt;Rhttp://purl.org/ontology/mo/Membership -->
<g id="edge40" class="edge"><title>B_:genid2&#45;&gt;Rhttp://purl.org/ontology/mo/Membership</title>
<path fill="none" stroke="black" d="M1559.08,-110.748C1655.93,-109.293 2114.2,-101.066 2253,-74 2277,-69.3192 2281.08,-61.103 2305,-56 2394.88,-36.8236 2419.46,-46.1212 2511,-38 2530.12,-36.304 2550.21,-34.5099 2570.08,-32.7283"/>
<polygon fill="black" stroke="black" points="2570.48,-36.2064 2580.13,-31.8268 2569.86,-29.2344 2570.48,-36.2064"/>
<text text-anchor="middle" x="2332" y="-60.9" font-family="Times Roman,serif" font-size="14.00">rdf:type</text>
</g>
<!-- Rhttp://njh.me/#Tom_Araya -->
<g id="node41" class="node"><title>Rhttp://njh.me/#Tom_Araya</title>
<a xlink:href="http://njh.me/#Tom_Araya" xlink:title="http://njh.me/#Tom_Araya">
<ellipse fill="none" stroke="blue" cx="1034" cy="-19" rx="137.782" ry="18"/>
<text text-anchor="middle" x="1034" y="-14.9" font-family="Times Roman,serif" font-size="14.00">http://njh.me/#Tom_Araya</text>
</a>
</g>
<!-- B_:genid2&#45;&gt;Rhttp://njh.me/#Tom_Araya -->
<g id="edge42" class="edge"><title>B_:genid2&#45;&gt;Rhttp://njh.me/#Tom_Araya</title>
<path fill="none" stroke="black" d="M1527.14,-99.4234C1523.12,-96.5851 1518.57,-93.8379 1514,-92 1505.26,-88.4885 1274.64,-54.2805 1136.3,-33.9619"/>
<polygon fill="black" stroke="black" points="1136.49,-30.4531 1126.09,-32.4633 1135.48,-37.3788 1136.49,-30.4531"/>
</g>
<!-- Lcurrent, vocal, bass -->
<g id="node43" class="node"><title>Lcurrent, vocal, bass</title>
<polygon fill="none" stroke="black" points="1189.5,-1 1189.5,-37 1340.5,-37 1340.5,-1 1189.5,-1"/>
<text text-anchor="middle" x="1265" y="-14.9" font-family="Times Roman,serif" font-size="14.00">current, vocal, bass</text>
</g>
<!-- B_:genid2&#45;&gt;Lcurrent, vocal, bass -->
<g id="edge44" class="edge"><title>B_:genid2&#45;&gt;Lcurrent, vocal, bass</title>
<path fill="none" stroke="black" d="M1526.69,-99.6259C1522.73,-96.8551 1518.34,-94.0907 1514,-92 1484.21,-77.639 1406.68,-55.738 1345.98,-39.67"/>
<polygon fill="black" stroke="black" points="1346.57,-36.2063 1336.01,-37.043 1344.78,-42.9753 1346.57,-36.2063"/>
<text text-anchor="middle" x="1494.5" y="-60.9" font-family="Times Roman,serif" font-size="14.00">rdfs:label</text>
</g>
<!-- Rhttp://dbpedia.org/page/Bass_guitar -->
<g id="node45" class="node"><title>Rhttp://dbpedia.org/page/Bass_guitar</title>
<a xlink:href="http://dbpedia.org/page/Bass_guitar" xlink:title="http://dbpedia.org/page/Bass_guitar">
<ellipse fill="none" stroke="blue" cx="1540" cy="-19" rx="182.059" ry="18"/>
<text text-anchor="middle" x="1540" y="-14.9" font-family="Times Roman,serif" font-size="14.00">http://dbpedia.org/page/Bass_guitar</text>
</a>
</g>
<!-- B_:genid2&#45;&gt;Rhttp://dbpedia.org/page/Bass_guitar -->
<g id="edge46" class="edge"><title>B_:genid2&#45;&gt;Rhttp://dbpedia.org/page/Bass_guitar</title>
<path fill="none" stroke="black" d="M1540.8,-92.8238C1540.66,-79.8451 1540.47,-62.1329 1540.31,-47.3112"/>
<polygon fill="black" stroke="black" points="1543.81,-47.0998 1540.2,-37.1385 1536.81,-47.176 1543.81,-47.0998"/>
</g>
<!-- L1982 -->
<g id="node47" class="node"><title>L1982</title>
<polygon fill="none" stroke="black" points="824,-1 824,-37 878,-37 878,-1 824,-1"/>
<text text-anchor="middle" x="851" y="-14.9" font-family="Times Roman,serif" font-size="14.00">1982</text>
</g>
<!-- B_:genid2&#45;&gt;L1982 -->
<g id="edge48" class="edge"><title>B_:genid2&#45;&gt;L1982</title>
<path fill="none" stroke="black" d="M1527.23,-99.2123C1523.2,-96.3732 1518.63,-93.6783 1514,-92 1467.88,-75.2989 1342.88,-78.161 1294,-74 1116.33,-58.8741 1063.09,-88.2941 887.838,-37.58"/>
<polygon fill="black" stroke="black" points="888.62,-34.162 878.039,-34.6986 886.646,-40.8777 888.62,-34.162"/>
</g>
<!-- B_:genid3&#45;&gt;Rhttp://purl.org/ontology/mo/Membership -->
<g id="edge50" class="edge"><title>B_:genid3&#45;&gt;Rhttp://purl.org/ontology/mo/Membership</title>
<path fill="none" stroke="black" d="M3066.84,-109.979C3001,-106.145 2777.28,-91.8994 2751,-74 2741.47,-67.5068 2734.84,-56.8523 2730.35,-46.6413"/>
<polygon fill="black" stroke="black" points="2733.55,-45.2052 2726.68,-37.1377 2727.02,-47.7272 2733.55,-45.2052"/>
<text text-anchor="middle" x="2778" y="-60.9" font-family="Times Roman,serif" font-size="14.00">rdf:type</text>
</g>
<!-- Rhttp://njh.me/#Paul_Bostaph -->
<g id="node50" class="node"><title>Rhttp://njh.me/#Paul_Bostaph</title>
<a xlink:href="http://njh.me/#Paul_Bostaph" xlink:title="http://njh.me/#Paul_Bostaph">
<ellipse fill="none" stroke="blue" cx="3164" cy="-19" rx="150.095" ry="18"/>
<text text-anchor="middle" x="3164" y="-14.9" font-family="Times Roman,serif" font-size="14.00">http://njh.me/#Paul_Bostaph</text>
</a>
</g>
<!-- B_:genid3&#45;&gt;Rhttp://njh.me/#Paul_Bostaph -->
<g id="edge52" class="edge"><title>B_:genid3&#45;&gt;Rhttp://njh.me/#Paul_Bostaph</title>
<path fill="none" stroke="black" d="M3097,-97.0272C3108.79,-83.2901 3127.09,-61.9882 3141.58,-45.1104"/>
<polygon fill="black" stroke="black" points="3144.48,-47.0999 3148.34,-37.2329 3139.17,-42.5395 3144.48,-47.0999"/>
</g>
<!-- Lcurrent, drums -->
<g id="node52" class="node"><title>Lcurrent, drums</title>
<polygon fill="none" stroke="black" points="3331.5,-1 3331.5,-37 3450.5,-37 3450.5,-1 3331.5,-1"/>
<text text-anchor="middle" x="3391" y="-14.9" font-family="Times Roman,serif" font-size="14.00">current, drums</text>
</g>
<!-- B_:genid3&#45;&gt;Lcurrent, drums -->
<g id="edge54" class="edge"><title>B_:genid3&#45;&gt;Lcurrent, drums</title>
<path fill="none" stroke="black" d="M3102.33,-105.79C3143.69,-93.3559 3250.03,-61.3834 3321.44,-39.914"/>
<polygon fill="black" stroke="black" points="3322.7,-43.1884 3331.27,-36.9574 3320.69,-36.4849 3322.7,-43.1884"/>
<text text-anchor="middle" x="3297.5" y="-60.9" font-family="Times Roman,serif" font-size="14.00">rdfs:label</text>
</g>
<!-- Rhttp://dbpedia.org/page/Drum_kit -->
<g id="node54" class="node"><title>Rhttp://dbpedia.org/page/Drum_kit</title>
<a xlink:href="http://dbpedia.org/page/Drum_kit" xlink:title="http://dbpedia.org/page/Drum_kit">
<ellipse fill="none" stroke="blue" cx="3995" cy="-19" rx="170.941" ry="18"/>
<text text-anchor="middle" x="3995" y="-14.9" font-family="Times Roman,serif" font-size="14.00">http://dbpedia.org/page/Drum_kit</text>
</a>
</g>
<!-- B_:genid3&#45;&gt;Rhttp://dbpedia.org/page/Drum_kit -->
<g id="edge56" class="edge"><title>B_:genid3&#45;&gt;Rhttp://dbpedia.org/page/Drum_kit</title>
<path fill="none" stroke="black" d="M3103.06,-109.231C3185.14,-101.183 3531.19,-67.1691 3815,-38 3830.92,-36.3638 3847.63,-34.6266 3864.19,-32.8934"/>
<polygon fill="black" stroke="black" points="3864.88,-36.3394 3874.46,-31.8157 3864.15,-29.3775 3864.88,-36.3394"/>
</g>
<!-- L2013 -->
<g id="node56" class="node"><title>L2013</title>
<polygon fill="none" stroke="black" points="2942,-1 2942,-37 2996,-37 2996,-1 2942,-1"/>
<text text-anchor="middle" x="2969" y="-14.9" font-family="Times Roman,serif" font-size="14.00">2013</text>
</g>
<!-- B_:genid3&#45;&gt;L2013 -->
<g id="edge58" class="edge"><title>B_:genid3&#45;&gt;L2013</title>
<path fill="none" stroke="black" d="M3070.78,-99.719C3053.21,-85.7878 3022.84,-61.6994 2999.83,-43.4535"/>
<polygon fill="black" stroke="black" points="3001.74,-40.4971 2991.73,-37.0254 2997.39,-45.9816 3001.74,-40.4971"/>
</g>
<!-- B_:genid4&#45;&gt;Rhttp://purl.org/ontology/mo/Membership -->
<g id="edge60" class="edge"><title>B_:genid4&#45;&gt;Rhttp://purl.org/ontology/mo/Membership</title>
<path fill="none" stroke="black" d="M3582.6,-110.679C3509.89,-109.235 3235.65,-102.121 3012,-74 2942.19,-65.2218 2863.84,-50.0379 2806.19,-37.845"/>
<polygon fill="black" stroke="black" points="2806.91,-34.4196 2796.4,-35.7607 2805.45,-41.2662 2806.91,-34.4196"/>
<text text-anchor="middle" x="3039" y="-60.9" font-family="Times Roman,serif" font-size="14.00">rdf:type</text>
</g>
<!-- B_:genid4&#45;&gt;Rhttp://dbpedia.org/page/Drum_kit -->
<g id="edge66" class="edge"><title>B_:genid4&#45;&gt;Rhttp://dbpedia.org/page/Drum_kit</title>
<path fill="none" stroke="black" d="M3619.06,-109.837C3657.58,-106.964 3750.28,-97.9421 3824,-74 3841.01,-68.4743 3843.29,-62.3949 3860,-56 3877.51,-49.2987 3896.72,-43.2765 3915.02,-38.1326"/>
<polygon fill="black" stroke="black" points="3916.07,-41.4734 3924.79,-35.4455 3914.22,-34.7243 3916.07,-41.4734"/>
</g>
<!-- B_:genid4&#45;&gt;L2013 -->
<g id="edge70" class="edge"><title>B_:genid4&#45;&gt;L2013</title>
<path fill="none" stroke="black" d="M3582.87,-109.834C3526.81,-106.113 3351.33,-93.6033 3207,-74 3119.73,-62.1459 3093.05,-67.2533 3005.64,-37.7002"/>
<polygon fill="black" stroke="black" points="3006.72,-34.3706 2996.12,-34.43 3004.44,-40.9905 3006.72,-34.3706"/>
</g>
<!-- Rhttp://njh.me/#Jon_Dette -->
<g id="node59" class="node"><title>Rhttp://njh.me/#Jon_Dette</title>
<a xlink:href="http://njh.me/#Jon_Dette" xlink:title="http://njh.me/#Jon_Dette">
<ellipse fill="none" stroke="blue" cx="3601" cy="-19" rx="132.918" ry="18"/>
<text text-anchor="middle" x="3601" y="-14.9" font-family="Times Roman,serif" font-size="14.00">http://njh.me/#Jon_Dette</text>
</a>
</g>
<!-- B_:genid4&#45;&gt;Rhttp://njh.me/#Jon_Dette -->
<g id="edge62" class="edge"><title>B_:genid4&#45;&gt;Rhttp://njh.me/#Jon_Dette</title>
<path fill="none" stroke="black" d="M3601,-92.8238C3601,-79.8451 3601,-62.1329 3601,-47.3112"/>
<polygon fill="black" stroke="black" points="3604.5,-47.1384 3601,-37.1385 3597.5,-47.1385 3604.5,-47.1384"/>
</g>
<!-- Llive, drums -->
<g id="node61" class="node"><title>Llive, drums</title>
<polygon fill="none" stroke="black" points="4184,-1 4184,-37 4276,-37 4276,-1 4184,-1"/>
<text text-anchor="middle" x="4230" y="-14.9" font-family="Times Roman,serif" font-size="14.00">live, drums</text>
</g>
<!-- B_:genid4&#45;&gt;Llive, drums -->
<g id="edge64" class="edge"><title>B_:genid4&#45;&gt;Llive, drums</title>
<path fill="none" stroke="black" d="M3619.13,-110.221C3689.7,-106.877 3952.6,-91.4897 4174.12,-37.9895"/>
<polygon fill="black" stroke="black" points="4175.09,-41.3554 4183.97,-35.5781 4173.42,-34.5561 4175.09,-41.3554"/>
<text text-anchor="middle" x="4114.5" y="-60.9" font-family="Times Roman,serif" font-size="14.00">rdfs:label</text>
</g>
<!-- L1996 -->
<g id="node64" class="node"><title>L1996</title>
<polygon fill="none" stroke="black" points="3752,-1 3752,-37 3806,-37 3806,-1 3752,-1"/>
<text text-anchor="middle" x="3779" y="-14.9" font-family="Times Roman,serif" font-size="14.00">1996</text>
</g>
<!-- B_:genid4&#45;&gt;L1996 -->
<g id="edge68" class="edge"><title>B_:genid4&#45;&gt;L1996</title>
<path fill="none" stroke="black" d="M3617.21,-102.736C3643.62,-89.2643 3697.52,-61.6914 3743,-38 3743.09,-37.9531 3743.18,-37.9061 3743.27,-37.859"/>
<polygon fill="black" stroke="black" points="3744.65,-41.0862 3751.89,-33.3482 3741.41,-34.8842 3744.65,-41.0862"/>
</g>
<!-- B_:genid5&#45;&gt;Rhttp://purl.org/ontology/mo/Membership -->
<g id="edge72" class="edge"><title>B_:genid5&#45;&gt;Rhttp://purl.org/ontology/mo/Membership</title>
<path fill="none" stroke="black" d="M4103.95,-109.576C4018.02,-102.835 3641.79,-73.7076 3333,-56 3155.33,-45.8117 3110.55,-49.983 2933,-38 2912.33,-36.6049 2890.54,-34.9039 2869.12,-33.0991"/>
<polygon fill="black" stroke="black" points="2869.24,-29.5967 2858.98,-32.2346 2868.65,-36.5714 2869.24,-29.5967"/>
<text text-anchor="middle" x="3643" y="-60.9" font-family="Times Roman,serif" font-size="14.00">rdf:type</text>
</g>
<!-- B_:genid5&#45;&gt;Rhttp://dbpedia.org/page/Drum_kit -->
<g id="edge78" class="edge"><title>B_:genid5&#45;&gt;Rhttp://dbpedia.org/page/Drum_kit</title>
<path fill="none" stroke="black" d="M4107.63,-100.123C4092.79,-88.9344 4068.91,-71.0644 4048,-56 4041.99,-51.6707 4035.56,-47.1144 4029.32,-42.7359"/>
<polygon fill="black" stroke="black" points="4031.19,-39.7736 4020.99,-36.9135 4027.18,-45.5111 4031.19,-39.7736"/>
</g>
<!-- B_:genid5&#45;&gt;Llive, drums -->
<g id="edge76" class="edge"><title>B_:genid5&#45;&gt;Llive, drums</title>
<path fill="none" stroke="black" d="M4136.12,-98.9726C4152.55,-84.9794 4180.1,-61.5097 4201.12,-43.6045"/>
<polygon fill="black" stroke="black" points="4203.47,-46.195 4208.82,-37.0459 4198.93,-40.8663 4203.47,-46.195"/>
<text text-anchor="middle" x="4217.5" y="-60.9" font-family="Times Roman,serif" font-size="14.00">rdfs:label</text>
</g>
<!-- Rhttp://njh.me/#Bob_Gourley -->
<g id="node68" class="node"><title>Rhttp://njh.me/#Bob_Gourley</title>
<a xlink:href="http://njh.me/#Bob_Gourley" xlink:title="http://njh.me/#Bob_Gourley">
<ellipse fill="none" stroke="blue" cx="4441" cy="-19" rx="146.816" ry="18"/>
<text text-anchor="middle" x="4441" y="-14.9" font-family="Times Roman,serif" font-size="14.00">http://njh.me/#Bob_Gourley</text>
</a>
</g>
<!-- B_:genid5&#45;&gt;Rhttp://njh.me/#Bob_Gourley -->
<g id="edge74" class="edge"><title>B_:genid5&#45;&gt;Rhttp://njh.me/#Bob_Gourley</title>
<path fill="none" stroke="black" d="M4139.39,-106.144C4164.5,-99.1208 4212.34,-85.6882 4253,-74 4293.33,-62.4053 4338.46,-49.2094 4374.4,-38.6498"/>
<polygon fill="black" stroke="black" points="4375.67,-41.9238 4384.27,-35.7449 4373.69,-35.2081 4375.67,-41.9238"/>
</g>
<!-- L1983 -->
<g id="node72" class="node"><title>L1983</title>
<polygon fill="none" stroke="black" points="4606,-1 4606,-37 4660,-37 4660,-1 4606,-1"/>
<text text-anchor="middle" x="4633" y="-14.9" font-family="Times Roman,serif" font-size="14.00">1983</text>
</g>
<!-- B_:genid5&#45;&gt;L1983 -->
<g id="edge80" class="edge"><title>B_:genid5&#45;&gt;L1983</title>
<path fill="none" stroke="black" d="M4140.19,-110.369C4203.22,-107.742 4417.76,-95.1146 4596.35,-37.6313"/>
<polygon fill="black" stroke="black" points="4597.49,-40.9418 4605.9,-34.5024 4595.31,-34.2896 4597.49,-40.9418"/>
</g>
<!-- B_:genid6&#45;&gt;L1981 -->
<g id="edge90" class="edge"><title>B_:genid6&#45;&gt;L1981</title>
<path fill="none" stroke="black" d="M2093.98,-108.896C2020.32,-100.399 1734.81,-68.4706 1499,-56 1439.41,-52.8486 513.473,-53.3035 388.561,-36.895"/>
<polygon fill="black" stroke="black" points="388.841,-33.39 378.383,-35.0887 387.618,-40.2823 388.841,-33.39"/>
</g>
<!-- B_:genid6&#45;&gt;Rhttp://purl.org/ontology/mo/Membership -->
<g id="edge82" class="edge"><title>B_:genid6&#45;&gt;Rhttp://purl.org/ontology/mo/Membership</title>
<path fill="none" stroke="black" d="M2129.93,-108.296C2199.81,-97.7572 2457.54,-58.8856 2608.95,-36.0501"/>
<polygon fill="black" stroke="black" points="2609.85,-39.4542 2619.22,-34.502 2608.81,-32.5325 2609.85,-39.4542"/>
<text text-anchor="middle" x="2499" y="-60.9" font-family="Times Roman,serif" font-size="14.00">rdf:type</text>
</g>
<!-- B_:genid6&#45;&gt;Rhttp://dbpedia.org/page/Guitar -->
<g id="edge88" class="edge"><title>B_:genid6&#45;&gt;Rhttp://dbpedia.org/page/Guitar</title>
<path fill="none" stroke="black" d="M2095.13,-103.781C2063.58,-90.2788 1994.52,-60.7291 1946.88,-40.346"/>
<polygon fill="black" stroke="black" points="1948.23,-37.1154 1937.66,-36.3991 1945.48,-43.551 1948.23,-37.1154"/>
</g>
<!-- B_:genid6&#45;&gt;L2013 -->
<g id="edge92" class="edge"><title>B_:genid6&#45;&gt;L2013</title>
<path fill="none" stroke="black" d="M2130.21,-110.702C2239.96,-108.827 2811.12,-97.974 2885,-74 2905.01,-67.5085 2924.81,-54.9186 2940.16,-43.4208"/>
<polygon fill="black" stroke="black" points="2942.44,-46.0815 2948.21,-37.1911 2938.16,-40.5472 2942.44,-46.0815"/>
</g>
<!-- Rhttp://njh.me/#Jeff_Hanneman -->
<g id="node75" class="node"><title>Rhttp://njh.me/#Jeff_Hanneman</title>
<a xlink:href="http://njh.me/#Jeff_Hanneman" xlink:title="http://njh.me/#Jeff_Hanneman">
<ellipse fill="none" stroke="blue" cx="2344" cy="-19" rx="157.933" ry="18"/>
<text text-anchor="middle" x="2344" y="-14.9" font-family="Times Roman,serif" font-size="14.00">http://njh.me/#Jeff_Hanneman</text>
</a>
</g>
<!-- B_:genid6&#45;&gt;Rhttp://njh.me/#Jeff_Hanneman -->
<g id="edge84" class="edge"><title>B_:genid6&#45;&gt;Rhttp://njh.me/#Jeff_Hanneman</title>
<path fill="none" stroke="black" d="M2130.03,-110.398C2176.88,-108.465 2300.86,-100.867 2330,-74 2337.39,-67.1823 2341.12,-57.0568 2342.92,-47.3455"/>
<polygon fill="black" stroke="black" points="2346.43,-47.506 2344.21,-37.1463 2339.48,-46.6292 2346.43,-47.506"/>
</g>
<!-- Lpast, guitar -->
<g id="node77" class="node"><title>Lpast, guitar</title>
<polygon fill="none" stroke="black" points="2072,-1 2072,-37 2168,-37 2168,-1 2072,-1"/>
<text text-anchor="middle" x="2120" y="-14.9" font-family="Times Roman,serif" font-size="14.00">past, guitar</text>
</g>
<!-- B_:genid6&#45;&gt;Lpast, guitar -->
<g id="edge86" class="edge"><title>B_:genid6&#45;&gt;Lpast, guitar</title>
<path fill="none" stroke="black" d="M2111.56,-92.62C2111.5,-81.91 2111.75,-68.16 2113,-56 2113.29,-53.23 2113.67,-50.3576 2114.11,-47.4934"/>
<polygon fill="black" stroke="black" points="2117.61,-47.8089 2115.89,-37.3538 2110.72,-46.5966 2117.61,-47.8089"/>
<text text-anchor="middle" x="2144.5" y="-60.9" font-family="Times Roman,serif" font-size="14.00">rdfs:label</text>
</g>
<!-- Rhttp://purl.org/ontology/mo/MuscialManifestation -->
<g id="node82" class="node"><title>Rhttp://purl.org/ontology/mo/MuscialManifestation</title>
<a xlink:href="http://purl.org/ontology/mo/MuscialManifestation" xlink:title="http://purl.org/ontology/mo/MuscialManifestation">
<ellipse fill="none" stroke="blue" cx="4994" cy="-19" rx="244.098" ry="18"/>
<text text-anchor="middle" x="4994" y="-14.9" font-family="Times Roman,serif" font-size="14.00">http://purl.org/ontology/mo/MuscialManifestation</text>
</a>
</g>
<!-- B_:genid7&#45;&gt;Rhttp://purl.org/ontology/mo/MuscialManifestation -->
<g id="edge94" class="edge"><title>B_:genid7&#45;&gt;Rhttp://purl.org/ontology/mo/MuscialManifestation</title>
<path fill="none" stroke="black" d="M4994,-92.8238C4994,-79.8451 4994,-62.1329 4994,-47.3112"/>
<polygon fill="black" stroke="black" points="4997.5,-47.1384 4994,-37.1385 4990.5,-47.1385 4997.5,-47.1384"/>
<text text-anchor="middle" x="5021" y="-60.9" font-family="Times Roman,serif" font-size="14.00">rdf:type</text>
</g>
<!-- LImplode -->
<g id="node84" class="node"><title>LImplode</title>
<polygon fill="none" stroke="black" points="5255.5,-1 5255.5,-37 5326.5,-37 5326.5,-1 5255.5,-1"/>
<text text-anchor="middle" x="5291" y="-14.9" font-family="Times Roman,serif" font-size="14.00">Implode</text>
</g>
<!-- B_:genid7&#45;&gt;LImplode -->
<g id="edge96" class="edge"><title>B_:genid7&#45;&gt;LImplode</title>
<path fill="none" stroke="black" d="M5008.24,-99.4763C5012.2,-96.7066 5016.61,-93.9803 5021,-92 5112.19,-50.8522 5146.83,-69.3377 5245.43,-38.2375"/>
<polygon fill="black" stroke="black" points="5246.75,-41.4894 5255.18,-35.0693 5244.59,-34.8324 5246.75,-41.4894"/>
<text text-anchor="middle" x="5205" y="-60.9" font-family="Times Roman,serif" font-size="14.00">dc11:title</text>
</g>
<!-- Rhttp://njh.me/Slayer -->
<g id="node86" class="node"><title>Rhttp://njh.me/Slayer</title>
<a xlink:href="http://njh.me/Slayer" xlink:title="http://njh.me/Slayer">
<ellipse fill="none" stroke="blue" cx="5451" cy="-19" rx="107.206" ry="18"/>
<text text-anchor="middle" x="5451" y="-14.9" font-family="Times Roman,serif" font-size="14.00">http://njh.me/Slayer</text>
</a>
</g>
<!-- B_:genid7&#45;&gt;Rhttp://njh.me/Slayer -->
<g id="edge98" class="edge"><title>B_:genid7&#45;&gt;Rhttp://njh.me/Slayer</title>
<path fill="none" stroke="black" d="M5007.77,-99.2112C5011.8,-96.3721 5016.36,-93.6775 5021,-92 5113.67,-58.4641 5144.86,-90.6041 5242,-74 5292.84,-65.309 5349.35,-50.0908 5390.78,-37.8624"/>
<polygon fill="black" stroke="black" points="5391.86,-41.1935 5400.44,-34.9839 5389.86,-34.4848 5391.86,-41.1935"/>
</g>
<!-- LSingle -->
<g id="node88" class="node"><title>LSingle</title>
<polygon fill="none" stroke="black" points="5575.5,-1 5575.5,-37 5634.5,-37 5634.5,-1 5575.5,-1"/>
<text text-anchor="middle" x="5605" y="-14.9" font-family="Times Roman,serif" font-size="14.00">Single</text>
</g>
<!-- B_:genid7&#45;&gt;LSingle -->
<g id="edge100" class="edge"><title>B_:genid7&#45;&gt;LSingle</title>
<path fill="none" stroke="black" d="M5007.76,-99.1624C5011.78,-96.3231 5016.35,-93.6405 5021,-92 5078.75,-71.6179 5235.06,-80.0357 5296,-74 5413.72,-62.3411 5449,-73.0607 5565.45,-38.0272"/>
<polygon fill="black" stroke="black" points="5566.55,-41.3499 5575.09,-35.0789 5564.51,-34.6558 5566.55,-41.3499"/>
</g>
<!-- L2014 -->
<g id="node90" class="node"><title>L2014</title>
<polygon fill="none" stroke="black" points="4678,-1 4678,-37 4732,-37 4732,-1 4678,-1"/>
<text text-anchor="middle" x="4705" y="-14.9" font-family="Times Roman,serif" font-size="14.00">2014</text>
</g>
<!-- B_:genid7&#45;&gt;L2014 -->
<g id="edge102" class="edge"><title>B_:genid7&#45;&gt;L2014</title>
<path fill="none" stroke="black" d="M4976.1,-107.167C4935.51,-98.2013 4833.51,-74.119 4741.67,-37.8921"/>
<polygon fill="black" stroke="black" points="4742.83,-34.5866 4732.24,-34.1168 4740.22,-41.0846 4742.83,-34.5866"/>
</g>
</g>
</svg>
